radiatreepp/__init__.py
radiatreepp/config.py
radiatreepp/core.py
radiatreepp/utils.py
radiatreepp-0.1.0.dist-info/METADATA
radiatreepp-0.1.0.dist-info/WHEEL
radiatreepp-0.1.0.dist-info/top_level.txt
radiatreepp-0.1.0.dist-info/RECORD
