Metadata-Version: 2.1
Name: radiatreepp
Version: 0.1.0
Summary: Radial dendrogram visualization for hierarchical clustering with feature importance overlays
Home-page: https://github.com/es15326/radialtreepp.git
Author: Elham Soltani Kazemi
Classifier: Programming Language :: Python :: 3
Classifier: License :: OSI Approved :: MIT License
Requires-Dist: numpy
Requires-Dist: pandas
Requires-Dist: scipy
Requires-Dist: matplotlib
